<?xml version="1.0" encoding="UTF-8" standalone="no"?><class><ITStudent><StudentId>85904633</StudentId><StudentName>JUSTIN JONES</StudentName><StudentProgramme>Bsc IT</StudentProgramme><StudentCourCode>CSC111</StudentCourCode><StudentMark>50</StudentMark></ITStudent><ITStudent><StudentId>85904633</StudentId><StudentName>JUSTIN JONES</StudentName><StudentProgramme>Bsc IT</StudentProgramme><StudentCourCode>ACS111</StudentCourCode><StudentMark>45</StudentMark></ITStudent><ITStudent><StudentId>85904633</StudentId><StudentName>JUSTIN JONES</StudentName><StudentProgramme>Bsc IT</StudentProgramme><StudentCourCode>GNS113</StudentCourCode><StudentMark>4</StudentMark></ITStudent><ITStudent><StudentId>85904633</StudentId><StudentName>JUSTIN JONES</StudentName><StudentProgramme>Bsc IT</StudentProgramme><StudentCourCode>ACF111</StudentCourCode><StudentMark>88</StudentMark></ITStudent><ITStudent><StudentId>85904633</StudentId><StudentName>JUSTIN JONES</StudentName><StudentProgramme>Bsc IT</StudentProgramme><StudentCourCode>ACF112</StudentCourCode><StudentMark>62</StudentMark></ITStudent><ITStudent><StudentId>85904633</StudentId><StudentName>JUSTIN JONES</StudentName><StudentProgramme>Bsc IT</StudentProgramme><StudentCourCode>CSC113</StudentCourCode><StudentMark>64</StudentMark></ITStudent><ITStudent><StudentId>85904633</StudentId><StudentName>JUSTIN JONES</StudentName><StudentProgramme>Bsc IT</StudentProgramme><StudentCourCode>MAT112</StudentCourCode><StudentMark>4</StudentMark></ITStudent><ITStudent><StudentId>85904633</StudentId><StudentName>JUSTIN JONES</StudentName><StudentProgramme>Bsc IT</StudentProgramme><StudentCourCode>CSC112</StudentCourCode><StudentMark>27</StudentMark></ITStudent><ITStudent><StudentId>85904633</StudentId><StudentName>JUSTIN JONES</StudentName><StudentProgramme>Bsc IT</StudentProgramme><StudentCourCode>BUS122</StudentCourCode><StudentMark>80</StudentMark></ITStudent><ITStudent><StudentId>85904633</StudentId><StudentName>JUSTIN JONES</StudentName><StudentProgramme>Bsc IT</StudentProgramme><StudentCourCode>BUS134</StudentCourCode><StudentMark>30</StudentMark></ITStudent></class>